xpclient/__init__.py
xpclient/api_client.py
xpclient/configuration.py
xpclient/rest.py
xpclient/utils.py
xpclient/version.py
xpclient/api/__init__.py
xpclient/api/xpctl_api.py
xpclient/models/__init__.py
xpclient/models/aggregate_result.py
xpclient/models/aggregate_result_values.py
xpclient/models/experiment.py
xpclient/models/experiment_aggregate.py
xpclient/models/response.py
xpclient/models/result.py
xpclient/models/task_summary.py
mead_xpctl_client-1.2.3.dist-info/LICENSE
mead_xpctl_client-1.2.3.dist-info/METADATA
mead_xpctl_client-1.2.3.dist-info/NOTICE
mead_xpctl_client-1.2.3.dist-info/WHEEL
mead_xpctl_client-1.2.3.dist-info/top_level.txt
mead_xpctl_client-1.2.3.dist-info/RECORD
